mapchete/__init__.py
mapchete/_deprecated.py
mapchete/bounds.py
mapchete/enums.py
mapchete/errors.py
mapchete/grid.py
mapchete/index.py
mapchete/log.py
mapchete/path.py
mapchete/pretty.py
mapchete/process_func_special_types.py
mapchete/protocols.py
mapchete/registered.py
mapchete/settings.py
mapchete/testing.py
mapchete/tile.py
mapchete/timer.py
mapchete/types.py
mapchete/validate.py
mapchete/zoom_levels.py
mapchete/cli/__init__.py
mapchete/cli/options.py
mapchete/cli/progress_bar.py
mapchete/cli/mapchete/__init__.py
mapchete/cli/mapchete/convert.py
mapchete/cli/mapchete/cp.py
mapchete/cli/mapchete/create.py
mapchete/cli/mapchete/execute.py
mapchete/cli/mapchete/formats.py
mapchete/cli/mapchete/index.py
mapchete/cli/mapchete/processes.py
mapchete/cli/mapchete/rm.py
mapchete/cli/mapchete/serve.py
mapchete/cli/mapchete/stac.py
mapchete/cli/mpath/__init__.py
mapchete/cli/mpath/cp.py
mapchete/cli/mpath/exists.py
mapchete/cli/mpath/ls.py
mapchete/cli/mpath/read_json.py
mapchete/cli/mpath/read_text.py
mapchete/cli/mpath/read_yaml.py
mapchete/cli/mpath/rm.py
mapchete/cli/mpath/sync.py
mapchete/commands/__init__.py
mapchete/commands/convert.py
mapchete/commands/cp.py
mapchete/commands/execute.py
mapchete/commands/index.py
mapchete/commands/observer.py
mapchete/commands/parser.py
mapchete/commands/rm.py
mapchete/config/__init__.py
mapchete/config/base.py
mapchete/config/models.py
mapchete/config/parse.py
mapchete/config/process_func.py
mapchete/executor/__init__.py
mapchete/executor/base.py
mapchete/executor/concurrent_futures.py
mapchete/executor/dask.py
mapchete/executor/future.py
mapchete/executor/sequential.py
mapchete/executor/types.py
mapchete/formats/__init__.py
mapchete/formats/base.py
mapchete/formats/drivers.py
mapchete/formats/loaders.py
mapchete/formats/protocols.py
mapchete/formats/tools.py
mapchete/formats/default/__init__.py
mapchete/formats/default/_fiona_base.py
mapchete/formats/default/flatgeobuf.py
mapchete/formats/default/geojson.py
mapchete-2025.12.0.dist-info/METADATA
mapchete-2025.12.0.dist-info/WHEEL
mapchete-2025.12.0.dist-info/entry_points.txt
mapchete-2025.12.0.dist-info/licenses/LICENSE
mapchete-2025.12.0.dist-info/RECORD
