Metadata-Version: 2.4
Name: mapchete
Version: 2025.12.0
Summary: Tile-based geodata processing using rasterio & Fiona
Project-URL: Homepage, https://github.com/ungarj/mapchete
Author-email: Joachim Ungar <joachim.ungar@gmail.com>
License-Expression: MIT
License-File: LICENSE
Classifier: Development Status :: 5 - Production/Stable
Classifier: Intended Audience :: Developers
Classifier: License :: OSI Approved :: MIT License
Classifier: Programming Language :: Python :: 3.10
Classifier: Programming Language :: Python :: 3.11
Classifier: Programming Language :: Python :: 3.12
Classifier: Programming Language :: Python :: 3.13
Classifier: Topic :: Scientific/Engineering :: GIS
Requires-Dist: aiohttp
Requires-Dist: cachetools
Requires-Dist: click-plugins
Requires-Dist: click-spinner
Requires-Dist: click>=7.1.1
Requires-Dist: dask
Requires-Dist: distributed
Requires-Dist: fiona>=1.8.13.post1
Requires-Dist: fsspec
Requires-Dist: geojson-pydantic
Requires-Dist: importlib-metadata
Requires-Dist: importlib-resources
Requires-Dist: numpy!=2.0.1,>=1.16
Requires-Dist: oyaml
Requires-Dist: pydantic-settings>=2.0.0
Requires-Dist: pydantic>=2.3.0
Requires-Dist: pyproj
Requires-Dist: pystac-client>=0.7.2
Requires-Dist: pystac[urllib3]>=1.8.2
Requires-Dist: python-dateutil
Requires-Dist: rasterio>1.2.10
Requires-Dist: retry
Requires-Dist: shapely>=2.0.0
Requires-Dist: tilematrix>=2022.12.0
Requires-Dist: tqdm
Provides-Extra: complete
Requires-Dist: aiobotocore<3.0.0,>=1.1.2; extra == 'complete'
Requires-Dist: aiohttp; extra == 'complete'
Requires-Dist: boto3>=1.14.44; extra == 'complete'
Requires-Dist: dask; extra == 'complete'
Requires-Dist: distributed; extra == 'complete'
Requires-Dist: flask-rangerequest; extra == 'complete'
Requires-Dist: flask<4.0.0; extra == 'complete'
Requires-Dist: fsspec[http,s3]>=2023.12.0; extra == 'complete'
Requires-Dist: lxml; extra == 'complete'
Requires-Dist: matplotlib<3.10; extra == 'complete'
Requires-Dist: memray; extra == 'complete'
Requires-Dist: pystac[urllib3]>=1.8.2; extra == 'complete'
Requires-Dist: requests; extra == 'complete'
Requires-Dist: rtree; extra == 'complete'
Requires-Dist: s3fs!=2023.9.0; extra == 'complete'
Requires-Dist: tilebench; extra == 'complete'
Requires-Dist: werkzeug>=0.15; extra == 'complete'
Provides-Extra: contours
Requires-Dist: matplotlib<3.10; extra == 'contours'
Provides-Extra: http
Requires-Dist: aiohttp; extra == 'http'
Requires-Dist: fsspec[http]; extra == 'http'
Requires-Dist: requests; extra == 'http'
Provides-Extra: profiling
Requires-Dist: memray; extra == 'profiling'
Requires-Dist: tilebench; extra == 'profiling'
Provides-Extra: s3
Requires-Dist: aiobotocore<3.0.0,>=1.1.2; extra == 's3'
Requires-Dist: boto3>=1.14.44; extra == 's3'
Requires-Dist: fsspec[s3]; extra == 's3'
Requires-Dist: s3fs!=2023.9.0; extra == 's3'
Provides-Extra: serve
Requires-Dist: flask-rangerequest; extra == 'serve'
Requires-Dist: flask<4.0.0; extra == 'serve'
Requires-Dist: werkzeug>=0.15; extra == 'serve'
Provides-Extra: spatial-index
Requires-Dist: rtree; extra == 'spatial-index'
Provides-Extra: test
Requires-Dist: coverage>=5.1; extra == 'test'
Requires-Dist: coveralls>=2.2.0; extra == 'test'
Requires-Dist: flake8>=3.8.4; extra == 'test'
Requires-Dist: minio; extra == 'test'
Requires-Dist: morecantile>=5.0.0; extra == 'test'
Requires-Dist: pystac; extra == 'test'
Requires-Dist: pytest-cov>=2.8.1; extra == 'test'
Requires-Dist: pytest-env; extra == 'test'
Requires-Dist: pytest-flask>=1.0.0; extra == 'test'
Requires-Dist: pytest-lazy-fixture>=0.6.3; extra == 'test'
Requires-Dist: pytest<8,>=5.4.1; extra == 'test'
Requires-Dist: rio-cogeo>=5.0.0; extra == 'test'
Provides-Extra: vrt
Requires-Dist: lxml; extra == 'vrt'
